{
  "test_name": "production_deployment_simulation",
  "timestamp": 1759160613.208098,
  "scenarios": [
    {
      "scenario": "high_load_simulation",
      "concurrent_requests": 3,
      "total_time": 19.849031207995722,
      "success_rate": 1.0,
      "results": [
        {
          "worker_id": 1,
          "response_length": 1717,
          "status": "success"
        },
        {
          "worker_id": 0,
          "response_length": 1084,
          "status": "success"
        },
        {
          "worker_id": 2,
          "response_length": 1241,
          "status": "success"
        }
      ],
      "status": "success"
    },
    {
      "scenario": "configuration_persistence",
      "error": "[Errno 2] No such file or directory: 'src/codomyrmex/language_models/outputs/config/config.json'",
      "status": "error"
    },
    {
      "scenario": "resource_cleanup",
      "instances_created": 6,
      "cleanup_successful": true,
      "status": "success"
    }
  ],
  "production_readiness": {
    "scenarios_passed": 2,
    "total_scenarios": 3,
    "readiness_score": 0.6666666666666666
  }
}